batcore/__init__.py
batcore/example.py
batcore/AliasMatching/__init__.py
batcore/AliasMatching/utils.py
batcore/Counter/BusFactorCounter.py
batcore/Counter/CoreWorkloadCounter.py
batcore/Counter/CounterBase.py
batcore/Counter/ExpertiseCounter.py
batcore/Counter/FaRCounter.py
batcore/Counter/__init__.py
batcore/Metrics/__init__.py
batcore/Metrics/metrics.py
batcore/RecommenderBase/__init__.py
batcore/RecommenderBase/recommender.py
batcore/baselines/__init__.py
batcore/baselines/utils.py
batcore/baselines/PRCF/PRCF.py
batcore/baselines/PRCF/__init__.py
batcore/baselines/PRCF/utils.py
batcore/baselines/models/ACRec.py
batcore/baselines/models/CN.py
batcore/baselines/models/RevFinder.py
batcore/baselines/models/RevRec.py
batcore/baselines/models/Tie.py
batcore/baselines/models/WRC.py
batcore/baselines/models/__init__.py
batcore/baselines/models/cHRev.py
batcore/baselines/models/xFinder.py
batcore/data/DataLoader.py
batcore/data/DatasetBase.py
batcore/data/GerritLoader.py
batcore/data/SpecialDatasets.py
batcore/data/StandardDataset.py
batcore/data/__init__.py
batcore/data/aggregators.py
batcore/data/utils.py
batcore/tester/RecTester.py
batcore/tester/SimulTester.py
batcore/tester/TesterBase.py
batcore/tester/__init__.py
batcore-0.1.1.dist-info/LICENSE
batcore-0.1.1.dist-info/METADATA
batcore-0.1.1.dist-info/WHEEL
batcore-0.1.1.dist-info/top_level.txt
batcore-0.1.1.dist-info/RECORD
