Metadata-Version: 2.1
Name: batcore
Version: 0.1.1
Summary: BaTCoRe
Author-email: Farid <kraalfar@gmail.com>
Project-URL: Homepage, https://github.com/JetBrains-Research/batcore
Project-URL: Bug Tracker, https://github.com/JetBrains-Research/batcore/issues
Project-URL: Docs, https://batcore.readthedocs.io/en/latest/index.html#
Classifier: Programming Language :: Python :: 3
Classifier: License :: OSI Approved :: Apache Software License
Classifier: Operating System :: OS Independent
Requires-Python: >=3.7
License-File: LICENSE
